[
  {"q":"What was Jesus' first miracle?","o":["Healing a leper","Walking on water","Turning water into wine","Raising Lazarus"],"a":2,"e":"John 2:11 — This, the first of his signs, Jesus performed at Cana in Galilee.","d":"easy"},
  {"q":"How many people did Jesus feed with five loaves and two fish?","o":["1,000","3,000","5,000 men","10,000"],"a":2,"e":"Matthew 14:21 — The number of those who ate was about five thousand men, besides women and children.","d":"easy"},
  {"q":"Who walked on water with Jesus?","o":["John","James","Peter","Andrew"],"a":2,"e":"Matthew 14:29 — Then Peter got down out of the boat, walked on the water and came toward Jesus.","d":"easy"},
  {"q":"How many people were raised from the dead in the Bible?","o":["1","3","7","8 or more"],"a":3,"e":"Various — Elijah, Elisha, Jesus, Peter, and Paul all performed or were involved in resurrections.","d":"hard"},
  {"q":"Which miracle did Elisha perform for the widow?","o":["Multiplied her oil","Healed her son of leprosy","Parted the Jordan","Turned water into wine"],"a":0,"e":"2 Kings 4:1-7 — Elisha multiplied the widow's oil to pay her debts.","d":"medium"},
  {"q":"What happened when Jesus touched the ear of the high priest's servant?","o":["It fell off","It was healed","It turned to gold","It became deaf"],"a":1,"e":"Luke 22:51 — And he touched his ear and healed him.","d":"medium"},
  {"q":"How many years had the woman with the issue of blood been suffering?","o":["7","10","12","40"],"a":2,"e":"Luke 8:43 — And a woman was there who had been subject to bleeding for twelve years.","d":"medium"},
  {"q":"Who was raised from the dead after being in the tomb for four days?","o":["Jairus' daughter","Lazarus","Tabitha","Eutychus"],"a":1,"e":"John 11:39 — 'By this time there is a bad odor, for he has been there four days.'","d":"easy"},
  {"q":"What did Jesus use to heal the blind man at Bethsaida?","o":["Mud and spit","His word only","Spit on his eyes","Oil"],"a":2,"e":"Mark 8:23 — He spit on the man’s eyes and put his hands on him.","d":"medium"},
  {"q":"How many lepers did Jesus heal at once?","o":["1","5","10","12"],"a":2,"e":"Luke 17:12-14 — Ten men who had leprosy met him.","d":"easy"},
  {"q":"How many of the ten healed lepers returned to thank Jesus?","o":["1","5","9","10"],"a":0,"e":"Luke 17:15-18 — One of them, when he saw he was healed, came back...","d":"easy"},
  {"q":"What did Peter find in the mouth of a fish to pay the temple tax?","o":["A pearl","A silver coin","A hook","A piece of bread"],"a":1,"e":"Matthew 17:27 — Take the first fish you catch; open its mouth and you will find a four-drachma coin.","d":"medium"},
  {"q":"Whose mother-in-law did Jesus heal of a fever?","o":["John's","James'","Peter's","Andrew's"],"a":2,"e":"Matthew 8:14-15 — Jesus saw Peter’s mother-in-law lying in bed with a fever... she got up and began to wait on him.","d":"medium"},
  {"q":"What did Jesus say to the storm on the Sea of Galilee?","o":["Stop now","Peace, be still","Quiet down","Go away"],"a":1,"e":"Mark 4:39 — He got up, rebuked the wind and said to the waves, 'Quiet! Be still!'","d":"easy"},
  {"q":"How many baskets of leftovers were collected after feeding the 5,000?","o":["3","7","12","40"],"a":2,"e":"Matthew 14:20 — They picked up twelve basketfuls of broken pieces that were left over.","d":"easy"},
  {"q":"Which prophet called down fire from heaven to consume a sacrifice?","o":["Elisha","Elijah","Moses","Samuel"],"a":1,"e":"1 Kings 18:38 — Then the fire of the Lord fell and burned up the sacrifice.","d":"easy"},
  {"q":"What happened to the sun during the battle at Gibeon?","o":["It was eclipsed","It stood still","It turned red","It vanished"],"a":1,"e":"Joshua 10:13 — The sun stopped in the middle of the sky and delayed going down about a full day.","d":"medium"},
  {"q":"What miracle did Peter perform on Aeneas?","o":["Healed him of paralysis","Raised him from the dead","Healed his blindness","Cast out a demon"],"a":0,"e":"Acts 9:33-34 — 'Aeneas,' Peter said to him, 'Jesus Christ heals you. Get up.'","d":"hard"},
  {"q":"Who was restored to life by Peter in Joppa?","o":["Lydia","Tabitha (Dorcas)","Rhoda","Priscilla"],"a":1,"e":"Acts 9:40 — Peter sent them all out of the room; then he got down on his knees and prayed. Turning toward the dead woman, he said, 'Tabitha, get up.'","d":"medium"},
  {"q":"How did Paul survive the bite of a poisonous viper on Malta?","o":["He drank an antidote","He shook it off into the fire and suffered no ill effects","The viper didn't bite him","He was healed by Luke"],"a":1,"e":"Acts 28:5 — But Paul shook the snake off into the fire and suffered no ill effects.","d":"medium"},
  {"q":"What miracle happened at the pool of Bethesda?","o":["The water turned to wine","An angel stirred the water for healing","The water parted","The water became gold"],"a":1,"e":"John 5:4 — From time to time an angel of the Lord would come down and stir up the waters.","d":"medium"},
  {"q":"Who was healed of leprosy after washing in the Jordan River seven times?","o":["Gehazi","Naaman","Uzziah","Simon"],"a":1,"e":"2 Kings 5:14 — So he went down and dipped himself in the Jordan seven times... and his flesh was restored.","d":"easy"},
  {"q":"What did Elisha do to make the iron ax head float?","o":["He prayed","He threw a stick into the water","He touched it with his staff","He commanded it to rise"],"a":1,"e":"2 Kings 6:6 — Elisha cut a stick and threw it there, and made the iron float.","d":"medium"},
  {"q":"What miracle did Jesus perform for the Centurion's servant?","o":["Healed him from a distance","Healed him by touch","Raised him from the dead","Cast out seven demons"],"a":0,"e":"Matthew 8:13 — Then Jesus said to the centurion, 'Go! Let it be done just as you believed it would.' And his servant was healed at that moment.","d":"medium"},
  {"q":"What was the name of the man Jesus healed of many demons, who lived in the tombs?","o":["Barabbas","Legion","Lazarus","Nicodemus"],"a":1,"e":"Mark 5:9 — Then Jesus asked him, 'What is your name?' 'My name is Legion,' he replied, 'for we are many.'","d":"medium"},
  {"q":"How many people were fed with seven loaves and a few small fish?","o":["3,000","4,000 men","5,000","10,000"],"a":1,"e":"Matthew 15:38 — The number of those who ate was four thousand men, besides women and children.","d":"medium"},
  {"q":"Which miracle did Jesus perform on the Sabbath that angered the Pharisees?","o":["Healed a man with a shriveled hand","Walking on water","Feeding the 5,000","Turning water into wine"],"a":0,"e":"Matthew 12:10-13 — Then he said to the man, 'Stretch out your hand.' He stretched it out and it was completely restored.","d":"medium"},
  {"q":"How did Jesus heal the man born blind in John 9?","o":["Spit on the ground, made mud, and put it on his eyes","Only said 'See!'","Touched his eyes","Anointed him with oil"],"a":0,"e":"John 9:6 — He spit on the ground, made some mud with the saliva, and put it on the man’s eyes.","d":"medium"},
  {"q":"What did the disciples think they saw when Jesus was walking on the water?","o":["A ghost","An angel","A boat","A sea monster"],"a":0,"e":"Matthew 14:26 — When the disciples saw him walking on the lake, they were terrified. 'It’s a ghost,' they said.","d":"easy"},
  {"q":"Whose ear was cut off and then healed by Jesus in the garden?","o":["Peter's","Malchus'","Caiaphas'","Judas'"],"a":1,"e":"John 18:10 — The servant’s name was Malchus. (Luke 22:51 mentions the healing).","d":"hard"},
  {"q":"What did Elisha do to the Shunammite woman's son?","o":["Healed his leprosy","Raised him from the dead","Healed his blindness","Healed his deafness"],"a":1,"e":"2 Kings 4:32-35 — Elisha went in, shut the door... and the boy sneezed seven times and opened his eyes.","d":"hard"},
  {"q":"How was the shadow on the sundial moved back ten steps for King Hezekiah?","o":["By a solar eclipse","By a miracle from God","By the prophet Isaiah's prayer","Both B and C"],"a":3,"e":"2 Kings 20:11 — Then the prophet Isaiah called on the Lord, and the Lord made the shadow go back.","d":"hard"},
  {"q":"What miracle happened when the Israelites carried the Ark into the Jordan River?","o":["The water turned to blood","The water stopped flowing/parted","The water became wine","A bridge appeared"],"a":1,"e":"Joshua 3:15-16 — As soon as the priests who carried the ark reached the Jordan... the water from upstream stopped flowing.","d":"medium"},
  {"q":"How did God provide water for the Israelites in the desert at Rephidim?","o":["Rain","Moses struck a rock","A new spring appeared","A well was found"],"a":1,"e":"Exodus 17:6 — Strike the rock, and water will come out of it for the people to drink.","d":"easy"},
  {"q":"What miracle did Paul perform in Lystra?","o":["Healed a man lame from birth","Raised a man from the dead","Blinded a sorcerer","Escaped from prison"],"a":0,"e":"Acts 14:8-10 — Paul looked at him... and called out, 'Stand up on your feet!' At that, the man jumped up and began to walk.","d":"hard"},
  {"q":"Who was blinded on the road to Damascus by a great light?","o":["Peter","Saul (Paul)","Stephen","Barnabas"],"a":1,"e":"Acts 9:3-9 — A light from heaven flashed around him... For three days he was blind.","d":"easy"},
  {"q":"What miracle happened to the prison doors while Paul and Silas were singing?","o":["They were opened by an angel","An earthquake opened them","They melted","The guards opened them"],"a":1,"e":"Acts 16:26 — Suddenly there was such a violent earthquake that the foundations of the prison were shaken. At once all the prison doors flew open.","d":"easy"},
  {"q":"How did Elisha heal the poisonous stew?","o":["By praying over it","By adding flour","By adding salt","By adding oil"],"a":1,"e":"2 Kings 4:41 — Elisha said, 'Get some flour.' He put it into the pot... and there was nothing harmful in the pot.","d":"hard"},
  {"q":"What did the prophet Isaiah use to heal King Hezekiah's boil?","o":["A poultice of figs","Oil","Holy water","A prayer cloth"],"a":0,"e":"2 Kings 20:7 — Then Isaiah said, 'Prepare a poultice of figs.' They did so and applied it to the boil, and he recovered.","d":"hard"},
  {"q":"What miracle did Elisha perform on the waters of Jericho?","o":["Parted them","Healed them with salt","Turned them to wine","Made them rise"],"a":1,"e":"2 Kings 2:21 — Then he went out to the spring and threw salt into it... 'I have healed this water.'","d":"hard"},
  {"q":"How many times did Elijah stretch himself over the widow's son to raise him?","o":["1","3","7","12"],"a":1,"e":"1 Kings 17:21 — Then he stretched himself out on the boy three times and cried out to the Lord.","d":"hard"},
  {"q":"What happened to the Egyptian chariots in the Red Sea before the water fell?","o":["Their wheels came off","They ran out of horses","They caught fire","They sank like lead"],"a":0,"e":"Exodus 14:25 — He jammed the wheels of their chariots so that they had difficulty driving.","d":"medium"},
  {"q":"Who was healed of leprosy after questioning Moses' authority?","o":["Aaron","Miriam","Korah","Dathan"],"a":1,"e":"Numbers 12:10 — When the cloud lifted from above the tent, Miriam's skin was leprous.","d":"medium"},
  {"q":"What miracle did God perform to show He had chosen Aaron?","o":["His staff budded and produced almonds","He was spared from fire","He walked on water","He spoke a new language"],"a":0,"e":"Numbers 17:8 — The next day Moses entered the tent... and Aaron’s staff... had not only sprouted but had budded, blossomed and produced almonds.","d":"medium"},
  {"q":"How was the wall of Jericho destroyed?","o":["By a battering ram","The people shouted and the wall fell","An earthquake","Fire from heaven"],"a":1,"e":"Joshua 6:20 — When the trumpets sounded, the army shouted, and at the sound of the trumpet, when the men gave a loud shout, the wall collapsed.","d":"easy"},
  {"q":"What miracle happened when the dead man's body touched Elisha's bones?","o":["The bones turned to gold","The man came back to life","The man was healed of leprosy","The earth opened up"],"a":1,"e":"2 Kings 13:21 — When the body touched Elisha’s bones, the man came to life and stood up on his feet.","d":"hard"},
  {"q":"How did Jesus heal the man lowered through the roof?","o":["Said his sins were forgiven and told him to walk","Touched his legs","Applied oil","Spit on him"],"a":0,"e":"Mark 2:5-12 — 'Son, your sins are forgiven... Get up, take your mat and go home.'","d":"medium"},
  {"q":"What was the result of Jesus cursing the fig tree?","o":["It produced fruit immediately","It withered and died","It grew taller","It turned into a vine"],"a":1,"e":"Matthew 21:19 — Immediately the tree withered.","d":"medium"},
  {"q":"Who was healed of blindness after Paul prayed for him in Malta?","o":["Publius","Publius' father","The Governor","The Centurion"],"a":1,"e":"Acts 28:8 — His father was sick in bed... Paul went in to see him and, after prayer, placed his hands on him and healed him.","d":"hard"},
  {"q":"What miracle occurred when Peter and John met the lame man at the Beautiful Gate?","o":["He was given gold","He was healed and began to walk and leap","He was given a new mat","He was raised from the dead"],"a":1,"e":"Acts 3:6-8 — 'In the name of Jesus Christ of Nazareth, walk.'... He jumped to his feet and began to walk.","d":"easy"}
]